Metadata-Version: 1.0
Name: math-binomial-gaussian-distribution
Version: 0.1
Summary: Gaussian distributions
Home-page: UNKNOWN
Author: Rishant Rokaha
Author-email: rixantrokaha@gmail.com
License: UNKNOWN
Platform: UNKNOWN
